[
 {
   "Name": "ד\"ר אורי אובולסקי",
   "EmailAddr": "uriobols@tauex.tau.ac.il",
   "WebsiteAddr": "https://uriobols.wixsite.com/obolskilab",
   "LinkedinProfile": "",
   "TwitterProfile": "",
   "Faculty": "סביבה ומדעי כדור הארץ"
 },
 {
   "Name": "ד\"ר אינס צוקר",
   "EmailAddr": "ineszucker@tauex.tau.ac.il",
   "WebsiteAddr": "https://zuckerlab.tau.ac.il/",
   "LinkedinProfile": "",
   "TwitterProfile": "",
   "Faculty": "סביבה ומדעי כדור הארץ"
 },
 {
   "Name": "ד\"ר אלון שפון",
   "EmailAddr": "alonshepon@tauex.tau.ac.il",
   "WebsiteAddr": "",
   "LinkedinProfile": "",
   "TwitterProfile": "",
   "Faculty": "סביבה ומדעי כדור הארץ"
 },
 {
   "Name": "ד\"ר אסף ענבל",
   "EmailAddr": "asafinbal@tauex.tau.ac.il",
   "WebsiteAddr": "",
   "LinkedinProfile": "",
   "TwitterProfile": "",
   "Faculty": "סביבה ומדעי כדור הארץ"
 },
 {
   "Name": "ד\"ר אריאל ללוש",
   "EmailAddr": "ariellel@tauex.tau.ac.il",
   "WebsiteAddr": "",
   "LinkedinProfile": "",
   "TwitterProfile": "",
   "Faculty": "סביבה ומדעי כדור הארץ"
 },
 {
   "Name": "ד\"ר דניאל משורי",
   "EmailAddr": "danim@tauex.tau.ac.il",
   "WebsiteAddr": "",
   "LinkedinProfile": "",
   "TwitterProfile": "",
   "Faculty": "סביבה ומדעי כדור הארץ"
 },
 {
   "Name": "ד\"ר ורד בלאס",
   "EmailAddr": "vblass@tauex.tau.ac.il",
   "WebsiteAddr": "https://www.tau.ac.il/profile/vblass",
   "LinkedinProfile": "",
   "TwitterProfile": "",
   "Faculty": "סביבה ומדעי כדור הארץ"
 },
 {
   "Name": "ד\"ר מיכל גרונטמן",
   "EmailAddr": "mgruntman@tauex.tau.ac.il",
   "WebsiteAddr": "https://michalgruntman.wixsite.com/plantecol",
   "LinkedinProfile": "",
   "TwitterProfile": "",
   "Faculty": "סביבה ומדעי כדור הארץ"
 },
 {
   "Name": "ד\"ר מיכל סגל רוזנהי",
   "EmailAddr": "msegalro@tauex.tau.ac.il",
   "WebsiteAddr": "https://www.clista.sites.tau.ac.il/",
   "LinkedinProfile": "",
   "TwitterProfile": "",
   "Faculty": "סביבה ומדעי כדור הארץ"
 },
 {
   "Name": "ד\"ר רועי ברקן",
   "EmailAddr": "rbarkan@tauex.tau.ac.il",
   "WebsiteAddr": "https://www.roybarkan.sites.tau.ac.il",
   "LinkedinProfile": "",
   "TwitterProfile": "",
   "Faculty": "סביבה ומדעי כדור הארץ"
 },
 {
   "Name": "פרופ' איל בן דור",
   "EmailAddr": "bendor@tauex.tau.ac.il",
   "WebsiteAddr": "https://www.tau.ac.il/~geograph/RSL/index.html",
   "LinkedinProfile": "",
   "TwitterProfile": "",
   "Faculty": "סביבה ומדעי כדור הארץ"
 },
 {
   "Name": "פרופ' איל חפץ",
   "EmailAddr": "eyalh@tauex.tau.ac.il",
   "WebsiteAddr": "https://eyalheifetz.weebly.com/",
   "LinkedinProfile": "",
   "TwitterProfile": "",
   "Faculty": "סביבה ומדעי כדור הארץ"
 },
 {
   "Name": "פרופ' אלון זיו",
   "EmailAddr": "zivalon@tauex.tau.ac.il",
   "WebsiteAddr": "https://tau.ac.il/~zivalon",
   "LinkedinProfile": "",
   "TwitterProfile": "",
   "Faculty": "סביבה ומדעי כדור הארץ"
 },
 {
   "Name": "פרופ' אלכסנדרה צ`ודנובסקי",
   "EmailAddr": "achudnov@tauex.tau.ac.il",
   "WebsiteAddr": "https://geography.tau.ac.il/en/?cmd=people.11&act=read&id=348",
   "LinkedinProfile": "",
   "TwitterProfile": "",
   "Faculty": "סביבה ומדעי כדור הארץ"
 },
 {
   "Name": "פרופ' גולברג אלכסנדר",
   "EmailAddr": "agolberg@tauex.tau.ac.il",
   "WebsiteAddr": "https://agolberg13.wixsite.com/my-site-1",
   "LinkedinProfile": "",
   "TwitterProfile": "",
   "Faculty": "סביבה ומדעי כדור הארץ"
 },
 {
   "Name": "פרופ' דרור אבישר",
   "EmailAddr": "droravi@tauex.tau.ac.il",
   "WebsiteAddr": "https://en-wrc.tau.ac.il/",
   "LinkedinProfile": "",
   "TwitterProfile": "",
   "Faculty": "סביבה ומדעי כדור הארץ"
 },
 {
   "Name": "פרופ' הדסה סערוני",
   "EmailAddr": "saaroni@tauex.tau.ac.il",
   "WebsiteAddr": "",
   "LinkedinProfile": "",
   "TwitterProfile": "",
   "Faculty": "סביבה ומדעי כדור הארץ"
 },
 {
   "Name": "פרופ' טובה [טובי] פנסטר",
   "EmailAddr": "tobiws@tauex.tau.ac.il",
   "WebsiteAddr": "https://www.tau.ac.il/~tobiws",
   "LinkedinProfile": "",
   "TwitterProfile": "",
   "Faculty": "סביבה ומדעי כדור הארץ"
 },
 {
   "Name": "פרופ' יצחק אומר",
   "EmailAddr": "omery@tauex.tau.ac.il",
   "WebsiteAddr": "https://urban-space-analysis-lab-tau.mozello.co.il/",
   "LinkedinProfile": "",
   "TwitterProfile": "",
   "Faculty": "סביבה ומדעי כדור הארץ"
 },
 {
   "Name": "פרופ' יצחק בננסון",
   "EmailAddr": "bennya@tauex.tau.ac.il",
   "WebsiteAddr": "https://www.geosimlab.org",
   "LinkedinProfile": "",
   "TwitterProfile": "",
   "Faculty": "סביבה ומדעי כדור הארץ"
 },
 {
   "Name": "פרופ' משה רשף",
   "EmailAddr": "mosher@tauex.tau.ac.il",
   "WebsiteAddr": "",
   "LinkedinProfile": "",
   "TwitterProfile": "",
   "Faculty": "סביבה ומדעי כדור הארץ"
 },
 {
   "Name": "פרופ' נילי הרניק",
   "EmailAddr": "harnik@tauex.tau.ac.il",
   "WebsiteAddr": "https://www.tau.ac.il/~harnik/",
   "LinkedinProfile": "",
   "TwitterProfile": "",
   "Faculty": "סביבה ומדעי כדור הארץ"
 },
 {
   "Name": "פרופ' קולין פרייס",
   "EmailAddr": "colin@tauex.tau.ac.il",
   "WebsiteAddr": "https://www.flash.sites.tau.ac.il",
   "LinkedinProfile": "",
   "TwitterProfile": "",
   "Faculty": "סביבה ומדעי כדור הארץ"
 },
 {
   "Name": "פרופ' רויטל [טלי] חתוקה",
   "EmailAddr": "hatuka@tauex.tau.ac.il",
   "WebsiteAddr": "https://lcud.tau.ac.il/",
   "LinkedinProfile": "",
   "TwitterProfile": "",
   "Faculty": "סביבה ומדעי כדור הארץ"
 },
 {
   "Name": "פרופ' שי יהושע יצחק צוקר",
   "EmailAddr": "shayz@tauex.tau.ac.il",
   "WebsiteAddr": "https://www.tau.ac.il/~shayz",
   "LinkedinProfile": "https://www.linkedin.com/in/shay-zucker-b794471/",
   "TwitterProfile": "",
   "Faculty": "סביבה ומדעי כדור הארץ"
 },
 {
   "Name": "פרופ' שמואל [שמוליק] מרקו",
   "EmailAddr": "shmulikm@tauex.tau.ac.il",
   "WebsiteAddr": "https://www.shmulik-marco.sites.tau.ac.il",
   "LinkedinProfile": "",
   "TwitterProfile": "",
   "Faculty": "סביבה ומדעי כדור הארץ"
 }
]